bloomerp/__init__.py
bloomerp/admin.py
bloomerp/apps.py
bloomerp/config.py
bloomerp/langchain_tools.py
bloomerp/middleware.py
bloomerp/signals.py
bloomerp/urls.py
bloomerp/components/bookmark.py
bloomerp/components/bulk_update_objects.py
bloomerp/components/bulk_upload_table.py
bloomerp/components/comments.py
bloomerp/components/create_workspace_item.py
bloomerp/components/data_table.py
bloomerp/components/datatable.py
bloomerp/components/datatable_and_filter.py
bloomerp/components/detail_view_links.py
bloomerp/components/download_bulk_upload_template.py
bloomerp/components/execute_sql_query.py
bloomerp/components/files.py
bloomerp/components/fk_search_results.py
bloomerp/components/list_view_filter.py
bloomerp/components/list_view_filter_inputs.py
bloomerp/components/object_model_form.py
bloomerp/components/search_results.py
bloomerp/components/sign_file.py
bloomerp/components/todos.py
bloomerp/components/document_templates/generate_document_template.py
bloomerp/components/llm/ai_conversations.py
bloomerp/components/llm/llm_executor.py
bloomerp/components/workspaces/reset_workspace.py
bloomerp/components/workspaces/workspace_widget.py
bloomerp/forms/auth.py
bloomerp/forms/core.py
bloomerp/forms/document_templates.py
bloomerp/forms/layouts.py
bloomerp/forms/widgets.py
bloomerp/management/commands/create_links.py
bloomerp/management/commands/get_urls.py
bloomerp/management/commands/remove_stale_links.py
bloomerp/management/commands/save_application_fields.py
bloomerp/management/commands/validate_form_layouts.py
bloomerp/migrations/0001_initial.py
bloomerp/migrations/0002_sqlquery_sqlqueryfilter_alter_file_file_kpi_and_more.py
bloomerp/migrations/0003_kpi_created_at_kpi_updated_at_sqlquery_created_at_and_more.py
bloomerp/migrations/0004_alter_file_file.py
bloomerp/migrations/0005_alter_file_file.py
bloomerp/migrations/0006_alter_file_file.py
bloomerp/migrations/0007_alter_file_file.py
bloomerp/migrations/0008_alter_file_file_alter_kpi_table_and_more.py
Bloomerp-0.3.1.dist-info/LICENSE.txt
Bloomerp-0.3.1.dist-info/METADATA
Bloomerp-0.3.1.dist-info/SOURCES.txt.py
Bloomerp-0.3.1.dist-info/WHEEL
Bloomerp-0.3.1.dist-info/dependency_links.txt.py
Bloomerp-0.3.1.dist-info/requires.txt.py
Bloomerp-0.3.1.dist-info/top_level.txt
Bloomerp-0.3.1.dist-info/top_level.txt.py
Bloomerp-0.3.1.dist-info/RECORD
