Metadata-Version: 2.1
Name: Bloomerp
Version: 0.3.1
Summary: Bloomerp is an open-source Business Management Software framework that lets you create fully functional business management applications just by defining your Django database models.
Home-page: https://github.com/davidbloomer11/Bloomerp
Author: David Bloomer
Author-email: bloomer.david@outlook.com
License: MIT License
Classifier: Environment :: Web Environment
Classifier: Framework :: Django
Classifier: Programming Language :: Python
Classifier: Programming Language :: Python :: 3
Classifier: Programming Language :: Python :: 3.12
Classifier: Operating System :: OS Independent
License-File: LICENSE.txt
Requires-Dist: requests >=2.0.0
Requires-Dist: djangorestframework >=3.12.0
Requires-Dist: django-htmx >=1.0.0
Requires-Dist: django-formtools >=2.3
Requires-Dist: Pillow >=8.0.0
Requires-Dist: psycopg2 ==2.9.9
Requires-Dist: django-crispy-forms >=2.2
Requires-Dist: django-filter >=24.3
Requires-Dist: crispy-bootstrap5 ==2024.2
Requires-Dist: xhtml2pdf >=0.2.16
Requires-Dist: pandas >=2.0.0
Requires-Dist: openpyxl >=3.1.5
Requires-Dist: openai >=1.54.1
Requires-Dist: plotly >=5.0.0
Requires-Dist: PyPDF2 >=3.0.1
Requires-Dist: langchain-core >=0.3.23
Requires-Dist: langchain-openai >=0.2.12
Requires-Dist: langgraph >=0.2.60
Requires-Dist: colorama >=0.4.6
Provides-Extra: images
Requires-Dist: Pillow >=8.0.0 ; extra == 'images'
